sigmund/__init__.py
sigmund/config.py
sigmund/documentation.py
sigmund/forms.py
sigmund/library.py
sigmund/messages.py
sigmund/process_sigmund_message.py
sigmund/prompt.py
sigmund/redis_client.py
sigmund/reply.py
sigmund/server.py
sigmund/sigmund.py
sigmund/static.py
sigmund/utils.py
sigmund/database/__init__.py
sigmund/database/encryption.py
sigmund/database/manager.py
sigmund/database/models.py
sigmund/model/__init__.py
sigmund/model/_anthropic_model.py
sigmund/model/_base_model.py
sigmund/model/_dummy_model.py
sigmund/model/_mistral_model.py
sigmund/model/_openai_model.py
sigmund/routes/__init__.py
sigmund/routes/api.py
sigmund/routes/app.py
sigmund/routes/google_login.py
sigmund/routes/public.py
sigmund/routes/subscribe.py
sigmund/static/anthropic.png
sigmund/static/background.png
sigmund/static/favicon.svg
sigmund/static/google.png
sigmund/static/loading.svg
sigmund/static/menu.css
sigmund/static/mistral.png
sigmund/static/openai.png
sigmund/static/opensesame.png
sigmund/static/pygments.css
sigmund/static/sigmund-avatar.png
sigmund/static/sofa-with-sigmund.png
sigmund/static/sofa.png
sigmund/static/terms.md
sigmund/templates/404.html
sigmund/templates/attachments.js
sigmund/templates/chat.html
sigmund/templates/error.html
sigmund/templates/footer.html
sigmund/templates/global_elements.js
sigmund/templates/head.html
sigmund/templates/header.html
sigmund/templates/health.js
sigmund/templates/info-page.html
sigmund/templates/login-div.html
sigmund/templates/login-failed.html
sigmund/templates/main.js
sigmund/templates/menu.html
sigmund/templates/search-widget.html
sigmund/templates/search-widget.js
sigmund/templates/sign-out.html
sigmund/templates/stylesheet.css.jinja
sigmund/templates/subscribe-error.html
sigmund/templates/subscribe-now.html
sigmund/templates/subscribe-success.html
sigmund/templates/websocket_client.js
sigmund/templates/welcome.html
sigmund/templates/workspace.js
sigmund/tools/__init__.py
sigmund/tools/_base_tool.py
sigmund-1.10.0.dist-info/licenses/COPYING
sigmund-1.10.0.dist-info/WHEEL
sigmund-1.10.0.dist-info/METADATA
sigmund-1.10.0.dist-info/RECORD
