Metadata-Version: 2.4
Name: sigmund
Version: 1.10.0
Summary: AI-based chatbot that provides sensible answers based on documentation
Keywords: ai,chatbot,llm
Author-email: Sebastiaan Mathôt <s.mathot@cogsci.nl>
Requires-Python: >=3.8
License-File: COPYING
Requires-Dist: anthropic
Requires-Dist: beautifulsoup4
Requires-Dist: cryptography
Requires-Dist: chromadb
Requires-Dist: datamatrix
Requires-Dist: flask
Requires-Dist: flask-login
Requires-Dist: flask-sqlalchemy
Requires-Dist: flask-wtf
Requires-Dist: flask-cors
Requires-Dist: flask-migrate
Requires-Dist: flask-session
Requires-Dist: jinja2
Requires-Dist: jq
Requires-Dist: markdown
Requires-Dist: oauthlib
Requires-Dist: openai
Requires-Dist: mistralai
Requires-Dist: pillow
Requires-Dist: pygments
Requires-Dist: pyopenssl
Requires-Dist: python-dotenv
Requires-Dist: redis
Requires-Dist: requests
Requires-Dist: scholarly
Requires-Dist: stripe
Requires-Dist: tiktoken
Requires-Dist: pytest ; extra == "test"
Requires-Dist: pytest-cov ; extra == "test"
Project-URL: Documentation, https://sigmundai.eu
Project-URL: Source, https://github.com/open-cogsci/sigmund-ai
Provides-Extra: test
